py2win/__init__.py
py2win/bdist_windows.py
py2win/embed.py
py2win/test_bdist_windows.py
py2win/test_embed.py
py2win-0.4.0.dist-info/LICENSE
py2win-0.4.0.dist-info/METADATA
py2win-0.4.0.dist-info/WHEEL
py2win-0.4.0.dist-info/top_level.txt
py2win-0.4.0.dist-info/RECORD
