Metadata-Version: 2.1
Name: py2win
Version: 0.4.0
Summary: Create a stand-alone Windows distribution of a Python program
Home-page: https://github.com/ppinard/py2win
Author: Philippe T. Pinard
Author-email: philippe.pinard@gmail.com
License: MIT
Platform: UNKNOWN
Classifier: Development Status :: 4 - Beta
Classifier: Intended Audience :: Developers
Classifier: License :: OSI Approved :: MIT License
Classifier: Natural Language :: English
Classifier: Programming Language :: Python
Classifier: Operating System :: Microsoft :: Windows
Classifier: Topic :: Software Development
License-File: LICENSE
Requires-Dist: wheel
Requires-Dist: requests
Requires-Dist: requests-cache
Requires-Dist: setuptools
